cardvalidator/formatter.py
cardvalidator/luhn.py
cardvalidator/__init__.py
Card_Validator-1.0.0.dist-info/DESCRIPTION.rst
Card_Validator-1.0.0.dist-info/METADATA
Card_Validator-1.0.0.dist-info/metadata.json
Card_Validator-1.0.0.dist-info/RECORD
Card_Validator-1.0.0.dist-info/top_level.txt
Card_Validator-1.0.0.dist-info/WHEEL
tests/formatter_spec.py
tests/luhn_spec.py
tests/__main__.py
